{
  "parent": "minecraft:recipes/root",
  "criteria": {
    "has_mangrove_timberplate": {
      "conditions": {
        "items": [
          {
            "items": "luckys_palette:mangrove_timberplate"
          }
        ]
      },
      "trigger": "minecraft:inventory_changed"
    },
    "has_the_recipe": {
      "conditions": {
        "recipe": "minecraft:mangrove_planks_from_mangrove_timberplate"
      },
      "trigger": "minecraft:recipe_unlocked"
    }
  },
  "requirements": [
    [
      "has_the_recipe",
      "has_mangrove_timberplate"
    ]
  ],
  "rewards": {
    "recipes": [
      "minecraft:mangrove_planks_from_mangrove_timberplate"
    ]
  }
}